mcp_obsidian_cloud/__init__.py
mcp_obsidian_cloud/remote_client.py
mcp_obsidian_cloud/server_final.py
mcp_obsidian_cloud/tools_pt.py
mcp_obsidian_cloud-0.2.1.dist-info/METADATA
mcp_obsidian_cloud-0.2.1.dist-info/WHEEL
mcp_obsidian_cloud-0.2.1.dist-info/entry_points.txt
mcp_obsidian_cloud-0.2.1.dist-info/RECORD
