Metadata-Version: 2.4
Name: mcp-obsidian-cloud
Version: 0.2.1
Summary: MCP server for Obsidian Cloud Stack - remote vault access
Author-email: Guilherme Giorgi <guilherme@ggailabs.com>
Requires-Dist: mcp>=1.0.0
Requires-Dist: pydantic>=2.0.0
Requires-Dist: requests>=2.25.0
